sorting_hat/__init__.py
sorting_hat/sorting_hat.py
sorting_hat-0.0.5.dist-info/METADATA
sorting_hat-0.0.5.dist-info/RECORD
sorting_hat-0.0.5.dist-info/WHEEL
sorting_hat-0.0.5.dist-info/entry_points.txt
sorting_hat-0.0.5.dist-info/top_level.txt
