Metadata-Version: 2.1
Name: sorting-hat
Version: 0.0.5
Summary: Sorts indels into mutational classes
Home-page: https://github.com/allisonseiden/sorting_hat
Author: Allison Seiden
Author-email: ahseiden@gmail.com
License: UNKNOWN
Platform: UNKNOWN
Classifier: Programming Language :: Python :: 3
Classifier: License :: OSI Approved :: MIT License
Classifier: Operating System :: OS Independent
Requires-Python: >=3
Requires-Dist: pandas
Requires-Dist: numpy
